{
  "wix-rich-content-plugin-button": 247,
  "wix-rich-content-plugin-code-block": 240,
  "wix-rich-content-plugin-collapsible-list": 237,
  "wix-rich-content-plugin-divider": 229,
  "wix-rich-content-plugin-emoji": 225,
  "wix-rich-content-plugin-file-upload": 253,
  "wix-rich-content-plugin-gallery": 501,
  "wix-rich-content-plugin-giphy": 229,
  "wix-rich-content-plugin-hashtag": 233,
  "wix-rich-content-plugin-headers-markdown": 224,
  "wix-rich-content-plugin-html": 236,
  "wix-rich-content-plugin-image": 265,
  "wix-rich-content-plugin-indent": 224,
  "wix-rich-content-plugin-line-spacing": 227,
  "wix-rich-content-plugin-link-preview": 240,
  "wix-rich-content-plugin-link": 232,
  "wix-rich-content-plugin-map": 352,
  "wix-rich-content-plugin-mentions": 227,
  "wix-rich-content-plugin-social-polls": 384,
  "wix-rich-content-plugin-sound-cloud": 311,
  "wix-rich-content-plugin-spoiler": 240,
  "wix-rich-content-plugin-table": 291,
  "wix-rich-content-plugin-text-color": 225,
  "wix-rich-content-plugin-undo-redo": 223,
  "wix-rich-content-plugin-vertical-embed": 232,
  "wix-rich-content-plugin-video": 319,
  "rcv": 161,
  "rcv-with-plugins": 257,
  "rcv-with-media-plugins": 600,
  "ricos-viewer": 187,
  "ricos-viewer-no-modal": 187,
  "ricos-viewer-with-plugins": 281,
  "rce": 789,
  "rce-with-plugins": 1024,
  "ricos-editor": 847,
  "ricos-editor-no-modal": 847,
  "ricos-editor-with-plugins": 1074,
  "ricos-common": 26,
  "ricos-content": 38,
  "rich-content-schema": 74,
  "converters": 127,
  "editor-common": 473
}